runcrate/__init__.py
runcrate/cli.py
runcrate/constants.py
runcrate/convert.py
runcrate/report.py
runcrate/run.py
runcrate/utils.py
runcrate-0.6.1.dist-info/LICENSE
runcrate-0.6.1.dist-info/METADATA
runcrate-0.6.1.dist-info/WHEEL
runcrate-0.6.1.dist-info/entry_points.txt
runcrate-0.6.1.dist-info/top_level.txt
runcrate-0.6.1.dist-info/RECORD
